nonebot_plugin_mahjong_hand_guess/__init__.py
nonebot_plugin_mahjong_hand_guess/assets/correct.png
nonebot_plugin_mahjong_hand_guess/assets/exist.png
nonebot_plugin_mahjong_hand_guess/assets/font/HYWenHei 65W.ttf
nonebot_plugin_mahjong_hand_guess/assets/font/HYWenHei 85W.ttf
nonebot_plugin_mahjong_hand_guess/assets/hands.txt
nonebot_plugin_mahjong_hand_guess/assets/no.png
nonebot_plugin_mahjong_hand_guess/assets/rule.png
nonebot_plugin_mahjong_hand_guess/db.py
nonebot_plugin_mahjong_hand_guess/handler.py
nonebot_plugin_mahjong_hand_guess/imghandler.py
nonebot_plugin_mahjong_hand_guess/mahjong_image.py
nonebot_plugin_mahjong_hand_guess/user.py
nonebot_plugin_majhong_hand_guess-0.2.0.dist-info/METADATA
nonebot_plugin_majhong_hand_guess-0.2.0.dist-info/WHEEL
nonebot_plugin_majhong_hand_guess-0.2.0.dist-info/licenses/LICENSE
nonebot_plugin_majhong_hand_guess-0.2.0.dist-info/RECORD
