Metadata-Version: 2.1
Name: nonebot-plugin-majhong-hand-guess
Version: 0.2.0
Summary: 日麻猜手牌小游戏（适用于Onebot V11）
Home-page: https://github.com/ElainaFanBoy/nonebot_plugin_mahjong_hand_guess
Author-Email: rf_tar_railt <3165388245@qq.com>, Nanako <demo0929@vip.qq.com>
License: MIT
Project-URL: Homepage, https://github.com/ElainaFanBoy/nonebot_plugin_mahjong_hand_guess
Project-URL: Repository, https://github.com/ElainaFanBoy/nonebot_plugin_mahjong_hand_guess
Requires-Python: <4.0,>=3.9
Requires-Dist: nonebot2<3.0.0,>=2.0.0
Requires-Dist: Pillow<10.0.0,>=9.5.0
Requires-Dist: ujson<6.0.0,>=5.7.0
Requires-Dist: mahjong<2.0.0,>=1.2.1
Requires-Dist: sqlitedict<3.0.0,>=2.1.0
Requires-Dist: nonebot-plugin-alconna>=0.47.0
Requires-Dist: nonebot-plugin-localstore>=0.6.0
